confobj/__init__.py
confobj/config.py
confobj/config_base.py
confobj/config_dict.py
confobj/config_env.py
confobj/config_ini.py
confobj/config_json.py
confobj/config_yaml.py
confobj-1.2.0.dist-info/DESCRIPTION.rst
confobj-1.2.0.dist-info/METADATA
confobj-1.2.0.dist-info/RECORD
confobj-1.2.0.dist-info/WHEEL
confobj-1.2.0.dist-info/metadata.json
confobj-1.2.0.dist-info/top_level.txt
