Metadata-Version: 2.0
Name: confobj
Version: 1.2.0
Summary: Object overridable by external configuration
Home-page: https://github.com/datasets-org/confobj
Author: Vit Listik
Author-email: tivvit@seznam.cz
License: MIT
Keywords: conf yaml json env
Platform: UNKNOWN
Classifier: Development Status :: 5 - Production/Stable
Classifier: Intended Audience :: Developers
Classifier: Topic :: Software Development :: Libraries
Classifier: License :: OSI Approved :: MIT License
Classifier: Programming Language :: Python :: 2
Classifier: Programming Language :: Python :: 2.7
Classifier: Programming Language :: Python :: 3
Classifier: Programming Language :: Python :: 3.2
Classifier: Programming Language :: Python :: 3.3
Classifier: Programming Language :: Python :: 3.4
Classifier: Programming Language :: Python :: 3.5
Classifier: Programming Language :: Python :: 3.6
Requires-Dist: pyYAML
Requires-Dist: typing
